{
    "version": "0.9.87",
    "description": "A modern terminal with built-in connection management and AI assistance.",
    "homepage": "https://yaw.sh",
    "license": {
        "identifier": "Proprietary",
        "url": "https://yaw.sh"
    },
    "architecture": {
        "64bit": {
            "url": "https://yaw.sh/downloads/yaw-win32-x64-0.9.87.zip",
            "hash": "284fe4756421397321a56330fe314cdb93574cbfa71d48a4d2b983bbffc37d50"
        },
        "arm64": {
            "url": "https://yaw.sh/downloads/yaw-win32-arm64-0.9.87.zip",
            "hash": "267996882510515fa9f7b0c24d38f63c1747a72b0442aa79bbd17e1729d84f4b"
        }
    },
    "bin": [
        "yaw.cmd",
        "yaw.exe"
    ],
    "shortcuts": [
        [
            "yaw.exe",
            "yaw"
        ]
    ],
    "checkver": {
        "url": "https://yaw.sh/version-windows.json",
        "jsonpath": "$.version"
    },
    "autoupdate": {
        "architecture": {
            "64bit": {
                "url": "https://yaw.sh/downloads/yaw-win32-x64-$version.zip"
            },
            "arm64": {
                "url": "https://yaw.sh/downloads/yaw-win32-arm64-$version.zip"
            }
        }
    }
}
