{
    "version": "2.0.8",
    "description": "A modern terminal with built-in connection management and AI assistance.",
    "homepage": "https://yaw.sh",
    "license": {
        "identifier": "Proprietary",
        "url": "https://yaw.sh"
    },
    "architecture": {
        "64bit": {
            "url": "https://downloads.yaw.sh/yaw-win32-x64-2.0.8.zip",
            "hash": "3035e84cb6cfd1c857e191f9228c0f85c90962ad34b8fd611669c2a5795c132c"
        },
        "arm64": {
            "url": "https://downloads.yaw.sh/yaw-win32-arm64-2.0.8.zip",
            "hash": "bc682d02317c04bede9d444c77630e424d6f86a002417aa7dd4f180d1c8bff25"
        }
    },
    "bin": [
        "yaw.cmd"
    ],
    "shortcuts": [
        [
            "yaw.exe",
            "yaw"
        ]
    ],
    "checkver": {
        "url": "https://yaw.sh/version-windows.json",
        "jsonpath": "$.version"
    },
    "autoupdate": {
        "architecture": {
            "64bit": {
                "url": "https://downloads.yaw.sh/yaw-win32-x64-$version.zip"
            },
            "arm64": {
                "url": "https://downloads.yaw.sh/yaw-win32-arm64-$version.zip"
            }
        }
    }
}
